flourishcharts/__init__.py
flourishcharts/_utils.py
flourishcharts/_version.py
flourishcharts/bindings.py
flourishcharts/details.py
flourishcharts/flourish.py
flourishcharts/data/flourish_api_documentation.csv
flourishcharts/data/gapminder.csv
flourishcharts/datasets/__init__.py
flourishcharts/datasets/gapminder.py
flourishcharts/flourish_docs/__init__.py
flourishcharts/flourish_docs/reference.py
flourishcharts/internal_data/internal_templates.csv
flourishcharts/static/widget.css
flourishcharts/static/widget.js
flourishcharts/tests/__init__.py
flourishcharts/tests/test_bindings.py
flourishcharts/tests/test_data.py
flourishcharts/tests/test_details.py
flourishcharts-1.6.5.6.dist-info/METADATA
flourishcharts-1.6.5.6.dist-info/WHEEL
flourishcharts-1.6.5.6.dist-info/licenses/LICENSE.txt
flourishcharts-1.6.5.6.dist-info/RECORD
