Metadata-Version: 2.4
Name: flourishcharts
Version: 1.6.5.6
Author-email: Zoe Meers <zoe.m@canva.com>, Alex Sadleir <alexs@canva.com>, Vincey Au <vincey@canva.com>, Luisa Bider <luisa@canva.com>
License: MIT
License-File: LICENSE.txt
Requires-Dist: anywidget
Requires-Dist: pandas
Requires-Dist: requests
Provides-Extra: dev
Requires-Dist: jupyterlab; extra == 'dev'
Requires-Dist: watchfiles; extra == 'dev'
